[
        {
            "imgSrc" : "piece-1.jpeg",
            "description" : "Design created using a feather and ink, for a company called Futon 24/7.",
            "alt" : "Piece 1"
        },
        {
            "imgSrc" : "piece-2.jpeg",
            "description" : "Inspired by Art Deco, this was created using linocutting and photoshop.",
            "alt" : "Piece 2"
        },
        {
            "imgSrc" : "piece-3.jpeg",
            "description" : "Inspired by Art Deco, this was created using linocutting and photoshop.",
            "alt" : "Piece 3"
        },
        {
            "imgSrc" : "piece-4.jpeg",
            "description" : "Inspired by Art Deco, this was created using linocutting and photoshop.",
            "alt" : "Piece 4"
        },
        {
            "imgSrc" : "piece-5.jpeg",
            "description" : "Inspired by Art Deco, this was created using linocutting and Photoshop.",
            "alt" : "Piece 5"
        },
        {
            "imgSrc" : "piece-6.jpeg",
            "description" : "Using Lino printing to create leaf patterns then further developed in Photoshop.",
            "alt" : "Piece 6"
        },
        {
            "imgSrc" : "piece-7.jpeg",
            "description" : "Inspired by pets and wildlife.",
            "alt" : "Piece 7"
        },
        {
            "imgSrc" : "piece-8.jpeg",
            "description" : "Inspired by pets and wildlife.",
            "alt" : "Piece 8"
        },
        {
            "imgSrc" : "piece-9.jpeg",
            "description" : "Plymouth architecture themed design. I used block printing techniques.",
            "alt" : "Piece 9"
        },
        {
            "imgSrc" : "piece-10.jpeg",
            "description" : "Batik wax with multiple layers of colour.",
            "alt" : "Piece 10"
        },
        {
            "imgSrc" : "piece-11.jpeg",
            "description" : "Using wax Batik to make a textured look.",
            "alt" : "Piece 11"
        },
        {
            "imgSrc" : "piece-12.jpeg",
            "description" : "Using Batik wax to make a textured look.",
            "alt" : "Piece 12"
        },
        {
            "imgSrc" : "piece-13.jpeg",
            "description" : "Using Batik wax to make a textured look.",
            "alt" : "Piece 13"
        },
        {
            "imgSrc" : "piece-14.jpeg",
            "description" : "Hand printed two colour Lino print.",
            "alt" : "Piece 14"
        },
        {
            "imgSrc" : "piece-15.jpeg",
            "description" : "Using synthetic materials to sublimate print my pattern onto the fabric.",
            "alt" : "Piece 15"
        },
        {
            "imgSrc" : "piece-16.jpeg",
            "description" : "Using various watered-down inks with string wrapped around a piece of woodblock.",
            "alt" : "Piece 16"
        },
        {
            "imgSrc" : "piece-17.jpeg",
            "description" : "",
            "alt" : "Piece 17"
        },
        {
            "imgSrc" : "piece-18.jpeg",
            "description" : "Picasso-themed collages inspired by various kitchen utensils.",
            "alt" : "Piece 18"
        },
        {
            "imgSrc" : "piece-19.jpeg",
            "description" : "Playing with collaging inspired by Matisse using various printing techniques",
            "alt" : "Piece 19"
        },
        {
            "imgSrc" : "piece-20.jpeg",
            "description" : "Playing with collaging inspired by Matisse using various printing techniques",
            "alt" : "Piece 20"
        },
        {
            "imgSrc" : "piece-21.jpeg",
            "description" : "Playing with collaging inspired by Matisse using various printing techniques",
            "alt" : "Piece 21"
        },
        {
            "imgSrc" : "piece-22.jpeg",
            "description" : "Inspired by traditional-style artwork/tattoos.",
            "alt" : "Piece 22"
        },
        {
            "imgSrc" : "piece-23.jpeg",
            "description" : "Inspired by traditional-style artwork/tattoos.",
            "alt" : "Piece 23"
        },
        {
            "imgSrc" : "piece-24.jpeg",
            "description" : "Inspired by traditional-style artwork/tattoos.",
            "alt" : "Piece 24"
        },
        {
            "imgSrc" : "piece-25.jpeg",
            "description" : "This project is called 'Traditional Summer'.",
            "alt" : "Piece 25"
        },
        {
            "imgSrc" : "piece-26.jpeg",
            "description" : "This project is called 'Traditional Summer'.",
            "alt" : "Piece 26"
        },
        {
            "imgSrc" : "piece-27.jpeg",
            "description" : "This project is called 'Traditional Summer'.",
            "alt" : "Piece 27"
        },
        {
            "imgSrc" : "piece-28.jpeg",
            "description" : "This project is called 'Traditional Summer'.",
            "alt" : "Piece 28"
        },
        {
            "imgSrc" : "piece-29.jpeg",
            "description" : "This project is called 'Traditional Summer'.",
            "alt" : "Piece 29"
        },
        {
            "imgSrc" : "piece-30.jpeg",
            "description" : "Looking at collage artwork which I developed into my patterns.",
            "alt" : "Piece 30"
        },
        {
            "imgSrc" : "piece-31.jpeg",
            "description" : "Looking at collage artwork which I developed into my patterns.",
            "alt" : "Piece 31"
        },
        {
            "imgSrc" : "piece-32.jpeg",
            "description" : "Inspired by fruit patterns",
            "alt" : "Piece 32"
        },
        {
            "imgSrc" : "piece-33.jpeg",
            "description" : "Inspired by fruit patterns",
            "alt" : "Piece 33"
        },
        {
            "imgSrc" : "piece-34.jpeg",
            "description" : "Inspired by fruit patterns",
            "alt" : "Piece 34"
        },
        {
            "imgSrc" : "piece-35.jpeg",
            "description" : "Using watercolour to paint tropical prints",
            "alt" : "Piece 35"
        },
        {
            "imgSrc" : "piece-36.jpeg",
            "description" : "Using watercolour to paint tropical prints",
            "alt" : "Piece 36"
        },
        {
            "imgSrc" : "piece-37.jpeg",
            "description" : "Traditional artwork inspired",
            "alt" : "Piece 37"
        },
        {
            "imgSrc" : "piece-38.jpeg",
            "description" : "Traditional artwork inspired",
            "alt" : "Piece 38"
        }
]